libela/__init__.py
libela/main.py
libela-0.0.3.dist-info/METADATA
libela-0.0.3.dist-info/WHEEL
libela-0.0.3.dist-info/top_level.txt
libela-0.0.3.dist-info/RECORD
