Metadata-Version: 2.1
Name: libela
Version: 0.0.3
Summary: A brief description of your package
Home-page: https://lib-ela.org
Author: Arya Amiri
Author-email: aryamiri@outlook.com
Classifier: Programming Language :: Python :: 3
Classifier: License :: OSI Approved :: MIT License
Classifier: Operating System :: OS Independent
